discord_anarchy/__init__.py
discord_anarchy/anarchy.py
discord_anarchy-0.0.1.dist-info/METADATA
discord_anarchy-0.0.1.dist-info/WHEEL
discord_anarchy-0.0.1.dist-info/top_level.txt
discord_anarchy-0.0.1.dist-info/RECORD
